texttable.py
texttable-1.6.6.data/data/stub/texttable.pyi
texttable-1.6.6.dist-info/LICENSE
texttable-1.6.6.dist-info/METADATA
texttable-1.6.6.dist-info/WHEEL
texttable-1.6.6.dist-info/top_level.txt
texttable-1.6.6.dist-info/RECORD
